{"_type":"export","__export_format":4,"__export_date":"2022-05-21T22:22:27.972Z","__export_source":"insomnia.desktop.app:v2021.5.3","resources":[{"_id":"req_6396b21baa904a4581e87498204f0a31","parentId":"fld_fc6745ebdbf943088e4e42b1ebf96cf2","modified":1651443213684,"created":1651442812240,"url":"{{ _.host }}:{{ _.port }}/api/content/create","name":"/api/content/create","description":"","method":"POST","body":{"mimeType":"application/json","text":"{\n\t\"type\": \"YouTube link-DDDDDD\",\n\t\"content\": \"https://www.youtube.com/watch?v=BTmHZMOirrI\",\n\t\"subject\": \"6269a95bd1f1fba2a1860ee6\",\n\t\"topic\": \"6269afb50ae1fcf14835795a\"\n}"},"parameters":[],"headers":[{"name":"Content-Type","value":"application/json","id":"pair_dab3abe496314be3ade25c01d805fa0f"}],"authentication":{"type":"bearer","token":"{{ _.token }}"},"metaSortKey":-1646727654958.8125,"isPrivate":false,"settingStoreCookies":true,"settingSendCookies":true,"settingDisableRenderRequestBody":false,"settingEncodeUrl":true,"settingRebuildPath":true,"settingFollowRedirects":"global","_type":"request"},{"_id":"fld_fc6745ebdbf943088e4e42b1ebf96cf2","parentId":"fld_ba11f357a5354d989f19e9924c8e0c6c","modified":1652976716877,"created":1651443201994,"name":"/content","description":"","environment":{},"environmentPropertyOrder":null,"metaSortKey":-1651443070343,"_type":"request_group"},{"_id":"fld_ba11f357a5354d989f19e9924c8e0c6c","parentId":"wrk_1d0bd65279c64477841f4c828c68d471","modified":1651442958935,"created":1651442958935,"name":"/api","description":"","environment":{},"environmentPropertyOrder":null,"metaSortKey":-1651442958935,"_type":"request_group"},{"_id":"wrk_1d0bd65279c64477841f4c828c68d471","parentId":null,"modified":1651442812077,"created":1651442812077,"name":"EduGuide","description":"","scope":"collection","_type":"workspace"},{"_id":"req_5cb6174bf3ee44339858abff4407a474","parentId":"fld_fc6745ebdbf943088e4e42b1ebf96cf2","modified":1653165383611,"created":1651442812242,"url":"{{ _.host }}:{{ _.port }}/api/content/6269b630f2b23d7b3fdd9bbb","name":"/api/content/:id","description":"","method":"GET","body":{},"parameters":[],"headers":[],"authentication":{"type":"bearer","token":"{{ _.token }}"},"metaSortKey":-1646727654908.8125,"isPrivate":false,"settingStoreCookies":true,"settingSendCookies":true,"settingDisableRenderRequestBody":false,"settingEncodeUrl":true,"settingRebuildPath":true,"settingFollowRedirects":"global","_type":"request"},{"_id":"req_235d65f5a6134ac9a110e225aad52573","parentId":"fld_fc6745ebdbf943088e4e42b1ebf96cf2","modified":1651443220101,"created":1651442812244,"url":"{{ _.host }}:{{ _.port }}/api/content/list","name":"/api/content/list","description":"","method":"GET","body":{},"parameters":[],"headers":[],"authentication":{"type":"bearer","token":"{{ _.token }}"},"metaSortKey":-1646727654858.8125,"isPrivate":false,"settingStoreCookies":true,"settingSendCookies":true,"settingDisableRenderRequestBody":false,"settingEncodeUrl":true,"settingRebuildPath":true,"settingFollowRedirects":"global","_type":"request"},{"_id":"req_d21813a550eb4770affdabc6570d80b1","parentId":"fld_fc6745ebdbf943088e4e42b1ebf96cf2","modified":1653165512226,"created":1651442812246,"url":"{{ _.host }}:{{ _.port }}/api/content/update","name":"/api/content/update","description":"","method":"POST","body":{"mimeType":"application/json","text":"{\n\t\"id\": \"62894cba29ef4532eddeebdd\",\n\t\"type\": \"YouTube link-DDDDDD-eeeeeeeeee\",\n\t\"content\": \"https://www.youtube.com/watch?v=BTmHZMOirrI\",\n\t\"subject\": \"6269a95bd1f1fba2a1860ee6\",\n\t\"topic\": \"6269afb50ae1fcf14835795a\"\n}"},"parameters":[],"headers":[{"name":"Content-Type","value":"application/json","id":"pair_9c9b1ec9dace46549690848b723091f0"}],"authentication":{"type":"bearer","token":"{{ _.token }}"},"metaSortKey":-1646727654808.8125,"isPrivate":false,"settingStoreCookies":true,"settingSendCookies":true,"settingDisableRenderRequestBody":false,"settingEncodeUrl":true,"settingRebuildPath":true,"settingFollowRedirects":"global","_type":"request"},{"_id":"req_238a4f2cafba4d5e956c7090712f21a9","parentId":"fld_fc6745ebdbf943088e4e42b1ebf96cf2","modified":1653165593209,"created":1651442812248,"url":"{{ _.host }}:{{ _.port }}/api/content/delete","name":"/api/content/delete","description":"","method":"POST","body":{"mimeType":"application/json","text":"{\n\t\"id\": \"62894cba29ef4532eddeebdd\"\n}"},"parameters":[],"headers":[{"name":"Content-Type","value":"application/json","id":"pair_73a0bd4eb08a40548d4b5ab64df4a886"}],"authentication":{"type":"bearer","token":"{{ _.token }}"},"metaSortKey":-1646727654758.8125,"isPrivate":false,"settingStoreCookies":true,"settingSendCookies":true,"settingDisableRenderRequestBody":false,"settingEncodeUrl":true,"settingRebuildPath":true,"settingFollowRedirects":"global","_type":"request"},{"_id":"req_58aca3850abb4f75af6d811ea1fb31c9","parentId":"fld_342e3f5f2b7146138be1d5ba6840ca4f","modified":1653164665180,"created":1651442812162,"url":"{{ _.host }}:{{ _.port }}/api/study-programme/create","name":"/api/study-programme/create","description":"","method":"POST","body":{"mimeType":"application/json","text":"{\n\t\"name\": \"Datová analýza - EEEEEE\",\n\t\"description\": \"Popis studijního programu Datová analýza\",\n\t\"supervisor\": \"6223e7f276b80392760dea94\",\n\t\"degree\": \"Bc.\",\n\t\"students\": [\"6222278da6d5a9361cbabf3a\", \"6223e7f276b80392760dea94\", \"62726f560b2192c52937bca9\"]\n}"},"parameters":[],"headers":[{"name":"Content-Type","value":"application/json","id":"pair_dab3abe496314be3ade25c01d805fa0f"}],"authentication":{"type":"bearer","token":"{{ _.token }}"},"metaSortKey":-1651442982247,"isPrivate":false,"settingStoreCookies":true,"settingSendCookies":true,"settingDisableRenderRequestBody":false,"settingEncodeUrl":true,"settingRebuildPath":true,"settingFollowRedirects":"global","_type":"request"},{"_id":"fld_342e3f5f2b7146138be1d5ba6840ca4f","parentId":"fld_ba11f357a5354d989f19e9924c8e0c6c","modified":1651443080794,"created":1651442982297,"name":"/study-programme","description":"","environment":{},"environmentPropertyOrder":null,"metaSortKey":-1651443070293,"_type":"request_group"},{"_id":"req_46677c94fd6e40cea99ca4ced81feaa7","parentId":"fld_342e3f5f2b7146138be1d5ba6840ca4f","modified":1653164826539,"created":1651442812169,"url":"{{ _.host }}:{{ _.port }}/api/study-programme/62894a7a2f868d8f73b392ae","name":"/api/study-programme/:id","description":"","method":"GET","body":{},"parameters":[],"headers":[],"authentication":{"type":"bearer","token":"{{ _.token }}"},"metaSortKey":-1651442982197,"isPrivate":false,"settingStoreCookies":true,"settingSendCookies":true,"settingDisableRenderRequestBody":false,"settingEncodeUrl":true,"settingRebuildPath":true,"settingFollowRedirects":"global","_type":"request"},{"_id":"req_7a9000411c9749e2b0308004e2137f1f","parentId":"fld_342e3f5f2b7146138be1d5ba6840ca4f","modified":1651443017832,"created":1651442812175,"url":"{{ _.host }}:{{ _.port }}/api/study-programme/list","name":"/api/study-programme/list","description":"","method":"GET","body":{},"parameters":[],"headers":[],"authentication":{"type":"bearer","token":"{{ _.token }}"},"metaSortKey":-1651442982147,"isPrivate":false,"settingStoreCookies":true,"settingSendCookies":true,"settingDisableRenderRequestBody":false,"settingEncodeUrl":true,"settingRebuildPath":true,"settingFollowRedirects":"global","_type":"request"},{"_id":"req_91e054569f8b484381c859c6d2254cdc","parentId":"fld_342e3f5f2b7146138be1d5ba6840ca4f","modified":1653164927191,"created":1651442812182,"url":"{{ _.host }}:{{ _.port }}/api/study-programme/update","name":"/api/study-programme/update","description":"","method":"POST","body":{"mimeType":"application/json","text":"{\n\t\"id\": \"62894a7a2f868d8f73b392ae\",\n\t\"name\": \"XXXXX - programovani 55 ----NEW\",\n\t\"description\": \"EDITED - programovani v javascript\",\n\t\"supervisor\": \"6223e7f276b80392760dea94\",\n\t\"degree\": \"Bc.\",\n\t\"students\": [\"6222278da6d5a9361cbabf3a\", \"6223e7f276b80392760dea94\", \"62726f560b2192c52937bca9\"]\n}"},"parameters":[],"headers":[{"name":"Content-Type","value":"application/json","id":"pair_9c9b1ec9dace46549690848b723091f0"}],"authentication":{"type":"bearer","token":"{{ _.token }}"},"metaSortKey":-1651442982097,"isPrivate":false,"settingStoreCookies":true,"settingSendCookies":true,"settingDisableRenderRequestBody":false,"settingEncodeUrl":true,"settingRebuildPath":true,"settingFollowRedirects":"global","_type":"request"},{"_id":"req_a99964e2878d4339bc0596bc8f8b05c1","parentId":"fld_342e3f5f2b7146138be1d5ba6840ca4f","modified":1653164992689,"created":1651442812190,"url":"{{ _.host }}:{{ _.port }}/api/study-programme/delete","name":"/api/study-programme/delete","description":"","method":"POST","body":{"mimeType":"application/json","text":"{\n\t\"id\": \"62894a7a2f868d8f73b392ae\"\n}"},"parameters":[],"headers":[{"name":"Content-Type","value":"application/json","id":"pair_73a0bd4eb08a40548d4b5ab64df4a886"}],"authentication":{"type":"bearer","token":"{{ _.token }}"},"metaSortKey":-1651442982047,"isPrivate":false,"settingStoreCookies":true,"settingSendCookies":true,"settingDisableRenderRequestBody":false,"settingEncodeUrl":true,"settingRebuildPath":true,"settingFollowRedirects":"global","_type":"request"},{"_id":"req_36683c4b7d7d464cabbddb338d36f26c","parentId":"fld_32363080c770485999e7e9af8610208f","modified":1653128598745,"created":1651442812198,"url":"{{ _.host }}:{{ _.port }}/api/subject/create","name":"/api/subject/create","description":"","method":"POST","body":{"mimeType":"application/json","text":"{\n\t\"name\": \"Programování ---NEW---\",\n\t\"goal\": \"Naučit studenty základům jazyka C/C++\",\n\t\"credits\": 6,\n\t\"supervisor\": \"6223e7f276b80392760dea94\",\n\t\"teachers\": [\"6223e7f276b80392760dea94\"],\n\t\"language\": \"cs\",\n\t\"studyProgramme\": \"6269a883d1f1fba2a1860edc\"\n}"},"parameters":[],"headers":[{"name":"Content-Type","value":"application/json","id":"pair_dab3abe496314be3ade25c01d805fa0f"}],"authentication":{"type":"bearer","token":"{{ _.token }}"},"metaSortKey":-1649824220396,"isPrivate":false,"settingStoreCookies":true,"settingSendCookies":true,"settingDisableRenderRequestBody":false,"settingEncodeUrl":true,"settingRebuildPath":true,"settingFollowRedirects":"global","_type":"request"},{"_id":"fld_32363080c770485999e7e9af8610208f","parentId":"fld_ba11f357a5354d989f19e9924c8e0c6c","modified":1651443070243,"created":1651443070243,"name":"/subject","description":"","environment":{},"environmentPropertyOrder":null,"metaSortKey":-1651443070243,"_type":"request_group"},{"_id":"req_b3a4b4c923074418a157451b4cfd7f3f","parentId":"fld_32363080c770485999e7e9af8610208f","modified":1653128101613,"created":1651442812206,"url":"{{ _.host }}:{{ _.port }}/api/subject/6269aaf6c7cbf76d1d83f1bd","name":"/api/subject/:id","description":"","method":"GET","body":{},"parameters":[],"headers":[],"authentication":{"type":"bearer","token":"{{ _.token }}"},"metaSortKey":-1649824220346,"isPrivate":false,"settingStoreCookies":true,"settingSendCookies":true,"settingDisableRenderRequestBody":false,"settingEncodeUrl":true,"settingRebuildPath":true,"settingFollowRedirects":"global","_type":"request"},{"_id":"req_dc4b35b116bb46528fa7d4657cb3645c","parentId":"fld_32363080c770485999e7e9af8610208f","modified":1653128082820,"created":1653128039988,"url":"{{ _.host }}:{{ _.port }}/api/subject/6269aaf6c7cbf76d1d83f1bd/contents","name":"/api/subject/:id/contents","description":"","method":"GET","body":{},"parameters":[],"headers":[],"authentication":{"type":"bearer","token":"{{ _.token }}"},"metaSortKey":-1649824220333.5,"isPrivate":false,"settingStoreCookies":true,"settingSendCookies":true,"settingDisableRenderRequestBody":false,"settingEncodeUrl":true,"settingRebuildPath":true,"settingFollowRedirects":"global","_type":"request"},{"_id":"req_f4bed2e6c8f64baf962176fa7d28d2b8","parentId":"fld_32363080c770485999e7e9af8610208f","modified":1653164019582,"created":1652568047143,"url":"{{ _.host }}:{{ _.port }}/api/subject/6269aaf6c7cbf76d1d83f1bd/topics","name":"/api/subject/:id/topics","description":"","method":"GET","body":{},"parameters":[],"headers":[],"authentication":{"type":"bearer","token":"{{ _.token }}"},"metaSortKey":-1649824220321,"isPrivate":false,"settingStoreCookies":true,"settingSendCookies":true,"settingDisableRenderRequestBody":false,"settingEncodeUrl":true,"settingRebuildPath":true,"settingFollowRedirects":"global","_type":"request"},{"_id":"req_b292831f8572461ca37f28c1aa4881eb","parentId":"fld_32363080c770485999e7e9af8610208f","modified":1651443095260,"created":1651442812214,"url":"{{ _.host }}:{{ _.port }}/api/subject/list","name":"/api/subject/list","description":"","method":"GET","body":{},"parameters":[],"headers":[],"authentication":{"type":"bearer","token":"{{ _.token }}"},"metaSortKey":-1649824220296,"isPrivate":false,"settingStoreCookies":true,"settingSendCookies":true,"settingDisableRenderRequestBody":false,"settingEncodeUrl":true,"settingRebuildPath":true,"settingFollowRedirects":"global","_type":"request"},{"_id":"req_12272cc6df2c41e98db8d6e55acda138","parentId":"fld_32363080c770485999e7e9af8610208f","modified":1653164341394,"created":1651442812222,"url":"{{ _.host }}:{{ _.port }}/api/subject/update","name":"/api/subject/update","description":"","method":"POST","body":{"mimeType":"application/json","text":"{\n\t\"id\": \"628946ae4213969744677760\",\n\t\"name\": \"Programování ---UPDATED---\",\n\t\"goal\": \"Naučit studenty základům jazyka JavaScript\",\n\t\"credits\": 29,\n\t\"supervisor\": \"6223e7f276b80392760dea94\",\n\t\"teachers\": [\"6223e7f276b80392760dea94\"],\n\t\"language\": \"cs\",\n\t\"studyProgramme\": \"6269a8abd1f1fba2a1860ee0\"\n}"},"parameters":[],"headers":[{"name":"Content-Type","value":"application/json","id":"pair_9c9b1ec9dace46549690848b723091f0"}],"authentication":{"type":"bearer","token":"{{ _.token }}"},"metaSortKey":-1649824220246,"isPrivate":false,"settingStoreCookies":true,"settingSendCookies":true,"settingDisableRenderRequestBody":false,"settingEncodeUrl":true,"settingRebuildPath":true,"settingFollowRedirects":"global","_type":"request"},{"_id":"req_fa84b7d4c0404652a681f3d671bb4dd3","parentId":"fld_32363080c770485999e7e9af8610208f","modified":1653164408799,"created":1651442812225,"url":"{{ _.host }}:{{ _.port }}/api/subject/delete","name":"/api/subject/delete","description":"","method":"POST","body":{"mimeType":"application/json","text":"{\n\t\"id\": \"628946ae4213969744677760\"\n}"},"parameters":[],"headers":[{"name":"Content-Type","value":"application/json","id":"pair_73a0bd4eb08a40548d4b5ab64df4a886"}],"authentication":{"type":"bearer","token":"{{ _.token }}"},"metaSortKey":-1649824220196,"isPrivate":false,"settingStoreCookies":true,"settingSendCookies":true,"settingDisableRenderRequestBody":false,"settingEncodeUrl":true,"settingRebuildPath":true,"settingFollowRedirects":"global","_type":"request"},{"_id":"req_9b27166a618343a88e009b13d8c1c9ac","parentId":"fld_f17a37d24ff54496945b572e2e32e70e","modified":1652005383280,"created":1651442812228,"url":"{{ _.host }}:{{ _.port }}/api/topic/create","name":"/api/topic/create","description":"","method":"POST","body":{"mimeType":"application/json","text":"{\n\t\"name\": \"03 Datové typy XXXXXX\",\n\t\"description\": \"\",\n\t\"subject\": \"6269a95bd1f1fba2a1860ee6\"\n}"},"parameters":[],"headers":[{"name":"Content-Type","value":"application/json","id":"pair_dab3abe496314be3ade25c01d805fa0f"}],"authentication":{"type":"bearer","token":"{{ _.token }}"},"metaSortKey":-1646727655208.8125,"isPrivate":false,"settingStoreCookies":true,"settingSendCookies":true,"settingDisableRenderRequestBody":false,"settingEncodeUrl":true,"settingRebuildPath":true,"settingFollowRedirects":"global","_type":"request"},{"_id":"fld_f17a37d24ff54496945b572e2e32e70e","parentId":"fld_ba11f357a5354d989f19e9924c8e0c6c","modified":1651443151618,"created":1651443148129,"name":"/topic","description":"","environment":{},"environmentPropertyOrder":null,"metaSortKey":-1651443070193,"_type":"request_group"},{"_id":"req_a5ce37dee68b465fb3c240b0f0b13c2a","parentId":"fld_f17a37d24ff54496945b572e2e32e70e","modified":1653161988803,"created":1651442812231,"url":"{{ _.host }}:{{ _.port }}/api/topic/6269afb50ae1fcf14835795a","name":"/api/topic/:id","description":"","method":"GET","body":{},"parameters":[],"headers":[],"authentication":{"type":"bearer","token":"{{ _.token }}"},"metaSortKey":-1646727655158.8125,"isPrivate":false,"settingStoreCookies":true,"settingSendCookies":true,"settingDisableRenderRequestBody":false,"settingEncodeUrl":true,"settingRebuildPath":true,"settingFollowRedirects":"global","_type":"request"},{"_id":"req_d75347e482ac462eb047f5a95e9cf0ee","parentId":"fld_f17a37d24ff54496945b572e2e32e70e","modified":1653162003882,"created":1653161934835,"url":"{{ _.host }}:{{ _.port }}/api/topic/6269afb50ae1fcf14835795a/contents","name":"/api/topic/:id/contents","description":"","method":"GET","body":{},"parameters":[],"headers":[],"authentication":{"type":"bearer","token":"{{ _.token }}"},"metaSortKey":-1646727655133.8125,"isPrivate":false,"settingStoreCookies":true,"settingSendCookies":true,"settingDisableRenderRequestBody":false,"settingEncodeUrl":true,"settingRebuildPath":true,"settingFollowRedirects":"global","_type":"request"},{"_id":"req_43d08c2989fb4315a9a9d5763896b363","parentId":"fld_f17a37d24ff54496945b572e2e32e70e","modified":1651443165449,"created":1651442812234,"url":"{{ _.host }}:{{ _.port }}/api/topic/list","name":"/api/topic/list","description":"","method":"GET","body":{},"parameters":[],"headers":[],"authentication":{"type":"bearer","token":"{{ _.token }}"},"metaSortKey":-1646727655108.8125,"isPrivate":false,"settingStoreCookies":true,"settingSendCookies":true,"settingDisableRenderRequestBody":false,"settingEncodeUrl":true,"settingRebuildPath":true,"settingFollowRedirects":"global","_type":"request"},{"_id":"req_3296bd7b4902438e959b5086b68ff45c","parentId":"fld_f17a37d24ff54496945b572e2e32e70e","modified":1653162238900,"created":1651442812236,"url":"{{ _.host }}:{{ _.port }}/api/topic/update","name":"/api/topic/update","description":"","method":"POST","body":{"mimeType":"application/json","text":"{\n\t\"id\": \"62893e53eff0fdba14e666f6\",\n\t\"name\": \"03 Datové typy XXXXXX-YYYYYYYYY\",\n\t\"description\": \"\",\n\t\"subject\": \"6269a95bd1f1fba2a1860ee6\"\n}"},"parameters":[],"headers":[{"name":"Content-Type","value":"application/json","id":"pair_9c9b1ec9dace46549690848b723091f0"}],"authentication":{"type":"bearer","token":"{{ _.token }}"},"metaSortKey":-1646727655058.8125,"isPrivate":false,"settingStoreCookies":true,"settingSendCookies":true,"settingDisableRenderRequestBody":false,"settingEncodeUrl":true,"settingRebuildPath":true,"settingFollowRedirects":"global","_type":"request"},{"_id":"req_2b13cf391e9e4a5c9b2248765afb0950","parentId":"fld_f17a37d24ff54496945b572e2e32e70e","modified":1653162344859,"created":1651442812238,"url":"{{ _.host }}:{{ _.port }}/api/topic/delete","name":"/api/topic/delete","description":"","method":"POST","body":{"mimeType":"application/json","text":"{\n\t\"id\": \"62893e53eff0fdba14e666f6\"\n}"},"parameters":[],"headers":[{"name":"Content-Type","value":"application/json","id":"pair_73a0bd4eb08a40548d4b5ab64df4a886"}],"authentication":{"type":"bearer","token":"{{ _.token }}"},"metaSortKey":-1646727655008.8125,"isPrivate":false,"settingStoreCookies":true,"settingSendCookies":true,"settingDisableRenderRequestBody":false,"settingEncodeUrl":true,"settingRebuildPath":true,"settingFollowRedirects":"global","_type":"request"},{"_id":"req_41f198bed4bc444990104d6e02d5a902","parentId":"fld_0a4f9b08622f44218d9ba89a1e1b1783","modified":1653171532189,"created":1652977009514,"url":"{{ _.host }}:{{ _.port }}/api/user/create","name":"/api/user/create","description":"","method":"POST","body":{"mimeType":"application/json","text":"{\n\t\"email\": \"test777@example.com\",\n\t\"thirdPartyIdentity\": false,\n\t\"name\": \"jmeno\",\n\t\"surname\": \"prijmeni\",\n\t\"password\": \"hesL5\",\n\t\"resetPassword\": false,\n\t\"groups\": [\"TEACHER\"]\n}"},"parameters":[],"headers":[{"name":"Content-Type","value":"application/json","id":"pair_d382a28e41a749f893f94b4bf868fb7c"}],"authentication":{"type":"bearer","token":"{{ _.token }}"},"metaSortKey":-1652977886601,"isPrivate":false,"settingStoreCookies":true,"settingSendCookies":true,"settingDisableRenderRequestBody":false,"settingEncodeUrl":true,"settingRebuildPath":true,"settingFollowRedirects":"global","_type":"request"},{"_id":"fld_0a4f9b08622f44218d9ba89a1e1b1783","parentId":"fld_ba11f357a5354d989f19e9924c8e0c6c","modified":1652976712293,"created":1652976657732,"name":"user","description":"","environment":{},"environmentPropertyOrder":null,"metaSortKey":-1651443070180.5,"_type":"request_group"},{"_id":"req_6906e5d5e9fd44e5897924164d46c999","parentId":"fld_0a4f9b08622f44218d9ba89a1e1b1783","modified":1653159757536,"created":1652977886551,"url":"{{ _.host }}:{{ _.port }}/api/user/6223e7f276b80392760dea94","name":"/api/user/:id","description":"","method":"GET","body":{},"parameters":[],"headers":[],"authentication":{"type":"bearer","token":"{{ _.token }}"},"metaSortKey":-1652977886551,"isPrivate":false,"settingStoreCookies":true,"settingSendCookies":true,"settingDisableRenderRequestBody":false,"settingEncodeUrl":true,"settingRebuildPath":true,"settingFollowRedirects":"global","_type":"request"},{"_id":"req_b3783d502ac94dbba0fd9ca47cf929a8","parentId":"fld_0a4f9b08622f44218d9ba89a1e1b1783","modified":1653070869472,"created":1652979513618,"url":"{{ _.host }}:{{ _.port }}/api/user/list","name":"/api/user/list","description":"","method":"GET","body":{},"parameters":[],"headers":[],"authentication":{"type":"bearer","token":"{{ _.token }}"},"metaSortKey":-1652977448032.5,"isPrivate":false,"settingStoreCookies":true,"settingSendCookies":true,"settingDisableRenderRequestBody":false,"settingEncodeUrl":true,"settingRebuildPath":true,"settingFollowRedirects":"global","_type":"request"},{"_id":"req_06f2120e79c94514ac203b3f68f2025a","parentId":"fld_0a4f9b08622f44218d9ba89a1e1b1783","modified":1653160971815,"created":1652999157919,"url":"{{ _.host }}:{{ _.port }}/api/user/update","name":"/api/user/update","description":"","method":"POST","body":{"mimeType":"application/json","text":"{\n\t\"id\": \"628935cbfba638496db8ab0d\",\n\t\"email\": \"test@example.com\",\n\t\"thirdPartyIdentity\": false,\n\t\"name\": \"UPDATED jmeno 4\",\n\t\"surname\": \"prijmeni\",\n\t\"groups\": [\"TEACHER\"]\n}"},"parameters":[],"headers":[{"name":"Content-Type","value":"application/json","id":"pair_a5e6b5f4a4ca48229fc9bf2537c2225c"}],"authentication":{"type":"bearer","token":"{{ _.token }}"},"metaSortKey":-1652977338402.875,"isPrivate":false,"settingStoreCookies":true,"settingSendCookies":true,"settingDisableRenderRequestBody":false,"settingEncodeUrl":true,"settingRebuildPath":true,"settingFollowRedirects":"global","_type":"request"},{"_id":"req_a067889a6fe44852a7cd635f69337e5d","parentId":"fld_0a4f9b08622f44218d9ba89a1e1b1783","modified":1653160746580,"created":1653160495244,"url":"{{ _.host }}:{{ _.port }}/api/user/update/password","name":"/api/user/update/password","description":"","method":"POST","body":{"mimeType":"application/json","text":"{\n\t\"id\": \"628935cbfba638496db8ab0d\",\n\t\"password\": \"NoveHeslo\"\n}"},"parameters":[],"headers":[{"name":"Content-Type","value":"application/json","id":"pair_e0f1847e2d9b4c5e8bd3dbdd4735eeb8"}],"authentication":{"type":"bearer","token":"{{ _.token }}"},"metaSortKey":-1652977283588.0625,"isPrivate":false,"settingStoreCookies":true,"settingSendCookies":true,"settingDisableRenderRequestBody":false,"settingEncodeUrl":true,"settingRebuildPath":true,"settingFollowRedirects":"global","_type":"request"},{"_id":"req_e460fcfa05334350946f6ff17e9c610a","parentId":"fld_0a4f9b08622f44218d9ba89a1e1b1783","modified":1653161111039,"created":1652993337283,"url":"{{ _.host }}:{{ _.port }}/api/user/delete","name":"/api/user/delete","description":"","method":"POST","body":{"mimeType":"application/json","text":"{\n\t\"id\": \"628935cbfba638496db8ab0d\"\n}"},"parameters":[],"headers":[{"name":"Content-Type","value":"application/json","id":"pair_5b5116996dfd4b74bb40791786dd9445"}],"authentication":{"type":"bearer","token":"{{ _.token }}"},"metaSortKey":-1652977228773.25,"isPrivate":false,"settingStoreCookies":true,"settingSendCookies":true,"settingDisableRenderRequestBody":false,"settingEncodeUrl":true,"settingRebuildPath":true,"settingFollowRedirects":"global","_type":"request"},{"_id":"req_2c15abd82e3e49528a198e74a94558c3","parentId":"fld_0a4f9b08622f44218d9ba89a1e1b1783","modified":1653071058817,"created":1653070825828,"url":"{{ _.host }}:{{ _.port }}/api/user/enum/teachers","name":"/api/user/enum/teachers","description":"","method":"GET","body":{},"parameters":[],"headers":[],"authentication":{"type":"bearer","token":"{{ _.token }}"},"metaSortKey":-1652977228723.25,"isPrivate":false,"settingStoreCookies":true,"settingSendCookies":true,"settingDisableRenderRequestBody":false,"settingEncodeUrl":true,"settingRebuildPath":true,"settingFollowRedirects":"global","_type":"request"},{"_id":"req_8bc279125e1c42b79d4205fa2181bf08","parentId":"fld_0a4f9b08622f44218d9ba89a1e1b1783","modified":1653071083501,"created":1653071079187,"url":"{{ _.host }}:{{ _.port }}/api/user/enum/students","name":"/api/user/enum/students","description":"","method":"GET","body":{},"parameters":[],"headers":[],"authentication":{"type":"bearer","token":"{{ _.token }}"},"metaSortKey":-1652210149408.125,"isPrivate":false,"settingStoreCookies":true,"settingSendCookies":true,"settingDisableRenderRequestBody":false,"settingEncodeUrl":true,"settingRebuildPath":true,"settingFollowRedirects":"global","_type":"request"},{"_id":"req_8b0e9a7383994d5594e9ca94590be8c3","parentId":"fld_ba11f357a5354d989f19e9924c8e0c6c","modified":1651443263316,"created":1651442812138,"url":"{{ _.host }}:{{ _.port }}/api/login","name":"/api/login","description":"","method":"POST","body":{"mimeType":"application/json","text":"{\n\t\"email\": \"jan@example.com\",\n\t\"password\": \"jan\"\n}"},"parameters":[],"headers":[{"name":"Content-Type","value":"application/json","id":"pair_0211b004496c4b94b1dacfee9edd9429"}],"authentication":{},"metaSortKey":-1651443070093,"isPrivate":false,"settingStoreCookies":true,"settingSendCookies":true,"settingDisableRenderRequestBody":false,"settingEncodeUrl":true,"settingRebuildPath":true,"settingFollowRedirects":"global","_type":"request"},{"_id":"req_1c2ad4fe43d344f289c58032c38a7e59","parentId":"fld_ba11f357a5354d989f19e9924c8e0c6c","modified":1652729296416,"created":1651442812147,"url":"{{ _.host }}:{{ _.port }}/api/signup","name":"/api/signup","description":"","method":"POST","body":{"mimeType":"application/json","text":"{\n\t\"email\": \"jan222@example.com\",\n\t\"password\": \"SecretPassword\",\n\t\"name\": \"Jan\",\n\t\"surname\": \"Janás\"\n}"},"parameters":[],"headers":[{"name":"Content-Type","value":"application/json","id":"pair_f301bb79181c443ba00c566813eed1ee"}],"authentication":{},"metaSortKey":-1651443070043,"isPrivate":false,"settingStoreCookies":true,"settingSendCookies":true,"settingDisableRenderRequestBody":false,"settingEncodeUrl":true,"settingRebuildPath":true,"settingFollowRedirects":"global","_type":"request"},{"_id":"req_aab73ea84cfc46da9ca010bced730600","parentId":"fld_ba11f357a5354d989f19e9924c8e0c6c","modified":1651443284449,"created":1651442812249,"url":"{{ _.host }}:{{ _.port }}/api/app/index","name":"/api/app/index","description":"","method":"GET","body":{},"parameters":[],"headers":[],"authentication":{"type":"bearer","token":"{{ _.token }}"},"metaSortKey":-1651443069943,"isPrivate":false,"settingStoreCookies":true,"settingSendCookies":true,"settingDisableRenderRequestBody":false,"settingEncodeUrl":true,"settingRebuildPath":true,"settingFollowRedirects":"global","_type":"request"},{"_id":"env_58f070ac8cd4493bb1facaa1df06164a","parentId":"wrk_1d0bd65279c64477841f4c828c68d471","modified":1651442812081,"created":1651442812081,"name":"Base Environment","data":{"token":"eyJhbGciOiJIUzI1NiIsInR5cCI6IkpXVCJ9.eyJ1c2VyIjp7ImlkIjoiNjIyM2U3ZjI3NmI4MDM5Mjc2MGRlYTk0IiwiZW1haWwiOiJqYW5AZXhhbXBsZS5jb20ifSwiaWF0IjoxNjUxNDM2NzY3fQ.LL651GeFMnZqQirS8Wk8PJ7SKz62L74vuZZ442ghZGc"},"dataPropertyOrder":{"&":["token"]},"color":null,"isPrivate":false,"metaSortKey":1646079934297,"_type":"environment"},{"_id":"jar_9ddec1c27d8c4f90a39a03c5a8cec0c5","parentId":"wrk_1d0bd65279c64477841f4c828c68d471","modified":1651442812111,"created":1651442812111,"name":"Default Jar","cookies":[],"_type":"cookie_jar"},{"_id":"spc_5bd8520013d54f4c81f19280dbe15b13","parentId":"wrk_1d0bd65279c64477841f4c828c68d471","modified":1651442812267,"created":1651442812118,"fileName":"EduGuide","contents":"","contentType":"yaml","_type":"api_spec"},{"_id":"env_6b226fa83784431794bacf1f1e0554f8","parentId":"env_58f070ac8cd4493bb1facaa1df06164a","modified":1651442812085,"created":1651442812085,"name":"localhost","data":{"host":"localhost","port":3000},"dataPropertyOrder":{"&":["host","port"]},"color":null,"isPrivate":false,"metaSortKey":1647127020326,"_type":"environment"},{"_id":"env_bdcc2421eaa64d9eac65834aff08eacb","parentId":"env_58f070ac8cd4493bb1facaa1df06164a","modified":1651442812100,"created":1651442812100,"name":"heroku","data":{},"dataPropertyOrder":null,"color":null,"isPrivate":false,"metaSortKey":1647127080266,"_type":"environment"}]}